wwo_hist/__init__.py
wwo_hist-0.0.6.dist-info/METADATA
wwo_hist-0.0.6.dist-info/WHEEL
wwo_hist-0.0.6.dist-info/top_level.txt
wwo_hist-0.0.6.dist-info/RECORD
