Metadata-Version: 2.1
Name: wwo-hist
Version: 0.0.6
Summary: This package is used to retrieve and transform historical weather data from www.worldweatheronline.com into pandas dataframe and csv.
Home-page: https://github.com/ekapope/WorldWeatherOnline
Author: Ekapope Viriyakovithya
Author-email: ekapope.v@gmail.com
License: UNKNOWN
Platform: UNKNOWN
Classifier: Programming Language :: Python :: 3
Classifier: License :: OSI Approved :: MIT License
Classifier: Operating System :: OS Independent
